celery_eye/__init__.py
celery_eye/admin.py
celery_eye/apps.py
celery_eye/models.py
celery_eye/signals.py
celery_eye/tests.py
celery_eye/urls.py
celery_eye/views.py
celery_eye/migrations/__init__.py
celery_eye-0.2.1.dist-info/licenses/LICENSE
celery_eye-0.2.1.dist-info/METADATA
celery_eye-0.2.1.dist-info/WHEEL
celery_eye-0.2.1.dist-info/top_level.txt
celery_eye-0.2.1.dist-info/RECORD
