Metadata-Version: 2.4
Name: celery-eye
Version: 0.2.1
Summary: Celery Eye - Django app to monitor and view Celery task logs in the admin panel
Author-email: Kush Rawal <kushrawal00@gmail.com>
License: MIT
Project-URL: Homepage, https://github.com/nullbite-coder/celery_eye
Requires-Python: >=3.7
License-File: LICENSE
Requires-Dist: Django>=5.0
Requires-Dist: celery>=5.4.0
Requires-Dist: redis>=4.0
Dynamic: license-file
